Metadata-Version: 1.1
Name: openapi-codec
Version: 0.0.4
Summary: An OpenAPI codec for Core API.
Home-page: http://github.com/encode/openapi-codec/
Author: Tom Christie
Author-email: tom@tomchristie.com
License: BSD
Platform: UNKNOWN
Classifier: Intended Audience :: Developers
Classifier: License :: OSI Approved :: BSD License
Classifier: Operating System :: OS Independent
Classifier: Programming Language :: Python
Classifier: Programming Language :: Python :: 3
